pytest_zephyr_scale_integration/__init__.py
pytest_zephyr_scale_integration/conftest.py
pytest_zephyr_scale_integration/integration.py
pytest_zephyr_scale_integration/utils.py
pytest_zephyr_scale_integration/zephyr_logger.py
pytest_zephyr_scale_integration-0.1.32.dist-info/LICENSE
pytest_zephyr_scale_integration-0.1.32.dist-info/METADATA
pytest_zephyr_scale_integration-0.1.32.dist-info/WHEEL
pytest_zephyr_scale_integration-0.1.32.dist-info/entry_points.txt
pytest_zephyr_scale_integration-0.1.32.dist-info/top_level.txt
pytest_zephyr_scale_integration-0.1.32.dist-info/RECORD
