Metadata-Version: 2.1
Name: pytest-zephyr-scale-integration
Version: 0.1.32
Summary: A library for integrating Jira Zephyr Scale (Adaptavist\TM4J) with pytest
Home-page: https://github.com/PROaction/pytest-zephyr-scale-integration
Author: Sergey Popov
Author-email: sergey1404sergey@mail.ru
Maintainer: Sergey Popov
Maintainer-email: sergey1404sergey@mail.ru
License: MIT
Keywords: zephyr,zephyr-scale,adaptavist,TM4J,pytest,autocreate test cycle,pytest zephyr integration
Classifier: Programming Language :: Python :: 3
Classifier: License :: OSI Approved :: MIT License
Classifier: Operating System :: OS Independent
Requires-Python: >=3.6
License-File: LICENSE
Requires-Dist: pytest
Requires-Dist: python-dotenv
Requires-Dist: requests
Requires-Dist: requests-toolbelt
